{"title":"You Can Now Play DOOM Directly On Bitcoin","type":"article","url":"https://blockworks.co/news/play-doom-bitcoin","image":"https://blockworks.co/_next/image?url=https://blockworks-co.imgix.net/wp-content/uploads/2023/02/doooom.jpg&w=1920&q=75&webp=false","image_secure_url":null,"image_type":null,"image_width":null,"image_height":null,"image_alt":"Blockworks","video":null,"video_secure_url":null,"video_type":null,"video_width":null,"video_height":null,"audio":null,"audio_secure_url":null,"audio_type":null,"description":"Ordinals’ Bitcoin NFTs are evolving, advancing from pixelated memes and pet rocks to a playable DOOM clone in a matter of days.","determiner":null,"locale":"en-US","locale_alternate":null,"site_name":"Blockworks","domain":"blockworks.co"}