{"title":"Ethereum NFT Card Battler ‘Parallel’ Launches on Epic Games Store - Decrypt","type":"article","url":"https://decrypt.co/235012/ethereum-nft-card-battler-parallel-epic-games-store","image":"https://cdn.decrypt.co/resize/1024/height/512/wp-content/uploads/2024/06/parallel-characters-gID_7.png","image_secure_url":null,"image_type":null,"image_width":null,"image_height":null,"image_alt":"Gaming Ethereum solana NFT Colony video games Epic Games Store Base Parallel","video":null,"video_secure_url":null,"video_type":null,"video_width":null,"video_height":null,"audio":null,"audio_secure_url":null,"audio_type":null,"description":"Competitive card game Parallel will be put in front of a monthly audience of 75 million active users ahead of a major esports push.","determiner":null,"locale":"en_US","locale_alternate":null,"site_name":"Decrypt","domain":"decrypt.co"}