{"title":"South Korea To Unveil Stringent Rules for Digital Assets, Here's All","type":"article","url":"https://coingape.com/south-korea-to-unveil-stringent-rules-for-digital-assets-heres-all/","image":"https://coingape.com/wp-content/uploads/2024/01/South-Korea-Crypto-ETF-Ban.jpg","image_secure_url":null,"image_type":"image/jpeg","image_width":"1200","image_height":"800","image_alt":null,"video":null,"video_secure_url":null,"video_type":null,"video_width":null,"video_height":null,"audio":null,"audio_secure_url":null,"audio_type":null,"description":"South Korea unveils comprehensive regulations under the Korean Virtual Asset User Protection Act, imposing stringent rules on NFTs deemed virtual assets, aiming to enhance oversight and transparency in the burgeoning digital asset market.","determiner":null,"locale":"en_US","locale_alternate":null,"site_name":"CoinGape","domain":"coingape.com"}